Metadata-Version: 1.0
Name: micropython-cpython-micropython
Version: 0.1.1
Summary: MicroPython module micropython ported to CPython
Home-page: https://github.com/pfalcon/micropython-lib
Author: Paul Sokolovsky
Author-email: micropython-lib@googlegroups.com
License: Python
Platform: UNKNOWN
